{
  "物种": "褐翅鸦鹃 (Centropus sinensis)",
  "数据类型": "详细现状分析",
  "保护现状": {
    "保护等级": {"中国": "国家二级重点保护野生动物", "IUCN": "无危 LC", "CITES": "未列入"},
    "全球种群数量": "约40万只（2025年估计，未精确量化）",
    "中国种群": "约12万只",
    "种群趋势": "稳定并逐步恢复"
  },
  "分布现状": {
    "分布概述": {
      "全球": ["孟加拉", "文莱", "柬埔寨", "中国", "印度", "印度尼西亚", "老挝", "马来西亚", "缅甸", "尼泊尔", "巴基斯坦", "斯里兰卡", "泰国", "越南"],
      "中国分布区域": "南方各省海拔800m以下低山丘陵和平原地区，为常见留鸟"
    },
    "中国亚种分布": {
      "指名亚种 (C. s. sinensis)": {"分布": ["云南东部", "贵州南部", "广西", "广东", "福建", "浙江"], "备注": "中国大部分地区为该亚种"},
      "云南亚种 (C. s. intermedius)": {"分布": ["海南岛", "云南南部", "云南西部"], "备注": "体型略小于指名亚种"}
    },
    "重要分布区": {
      "广东省": {"主要地点": ["海丰鸟类自然保护区", "湛江", "广州周边湿地"], "密度": "海丰夏季密度最高17.78只/km²", "备注": "国内密度最高的区域之一"},
      "广西壮族自治区": {"主要地点": ["弄岗保护区", "桂林", "北部湾沿海"], "密度": "中高"},
      "云南省": {"主要地点": ["西双版纳", "德宏", "红河"], "密度": "中高", "备注": "两个亚种均有分布"},
      "福建省": {"主要地点": ["闽江口", "厦门", "武夷山低海拔区"], "密度": "中"},
      "海南省": {"主要地点": ["全岛低海拔区域"], "密度": "中高"}
    }
  },
  "威胁因素": {
    "主要威胁": [
      {"类型": "历史猎捕", "严重程度": "已大幅降低", "详细说明": "20世纪50-60年代广东广西年猎捕量达数十万只用于制作中药；2021年列入国家二级保护后全面禁止"},
      {"类型": "栖息地碎片化", "严重程度": "中", "详细说明": "低海拔区域开发建设导致适宜生境减少"},
      {"类型": "农药使用", "严重程度": "低中", "详细说明": "农药减少昆虫等食物资源，可能通过食物链积累"}
    ]
  },
  "保护措施": ["2021年列入国家二级重点保护野生动物", "全面禁止猎捕和贸易", "低海拔湿地和林缘灌丛保护", "自然保护区网络覆盖", "公众教育宣传（普及'毛鸡酒'违法性）"],
  "生态价值": "低海拔灌丛生态系统重要指示物种，控制农田害虫和鼠类的重要天敌；作为一种非寄生性杜鹃，对研究杜鹃科演化具有独特价值",
  "数据说明": {"采集时间": "2025年", "主要参考来源": ["IUCN Red List (2024)", "BirdLife International", "广东海丰鸟类自然保护区调查报告", "《中国鸟类分类与分布名录》"]}
}
